pycgl/__init__.py
pycgl/__main__.py
pycgl/pycg.py
pycgl/formats/__init__.py
pycgl/formats/as_graph.py
pycgl/formats/base.py
pycgl/formats/fasten.py
pycgl/formats/simple.py
pycgl/machinery/__init__.py
pycgl/machinery/callgraph.py
pycgl/machinery/classes.py
pycgl/machinery/definitions.py
pycgl/machinery/imports.py
pycgl/machinery/key_err.py
pycgl/machinery/modules.py
pycgl/machinery/pointers.py
pycgl/machinery/scopes.py
pycgl/processing/__init__.py
pycgl/processing/base.py
pycgl/processing/cgprocessor.py
pycgl/processing/keyerrprocessor.py
pycgl/processing/postprocessor.py
pycgl/processing/preprocessor.py
pycgl/tests/base.py
pycgl/tests/callgraph_test.py
pycgl/tests/definitions_test.py
pycgl/tests/fasten_format_test.py
pycgl/tests/imports_test.py
pycgl/tests/pointers_test.py
pycgl/tests/scopes_test.py
pycgl/utils/__init__.py
pycgl/utils/common.py
pycgl/utils/constants.py
pycg_fork-0.0.8.dist-info/METADATA
pycg_fork-0.0.8.dist-info/WHEEL
pycg_fork-0.0.8.dist-info/licenses/LICENCE
pycg_fork-0.0.8.dist-info/RECORD
