Metadata-Version: 2.4
Name: pycg-fork
Version: 0.0.8
Summary: pycgl - Practical Python Call Graphs
Project-URL: Homepage, https://github.com/pavlatos/pycgl
Project-URL: Bug Tracker, https://github.com/pavlatos/pycgl/issues
Author-email: Vitalis Salis <vitsalis@gmail.com>, Spyros Pavlatos <pavlatos@seas.upenn.edu>
License:                                  Apache License
License-File: LICENCE
Classifier: License :: OSI Approved :: Apache Software License
Classifier: Programming Language :: Python :: 3
Requires-Python: >=3.4
Provides-Extra: dev
Requires-Dist: black>=22.12.0; extra == 'dev'
Requires-Dist: flake8>=6.0.0; extra == 'dev'
Requires-Dist: isort>=5.12.0; extra == 'dev'
Requires-Dist: mock; extra == 'dev'
